examples/__init__.py
examples/callback.py
examples/chat.py
examples/conf.py
examples/message.py
examples/mini_program.py
examples/service_corp.py
examples/service_provider.py
examples/shenpi.py
examples/user.py
wework/AbstractApi.py
wework/CorpApi.py
wework/ServiceCorpApi.py
wework/ServiceProviderApi.py
wework/WXBizMsgCrypt.py
wework/__init__.py
wework/ierror.py
wework-0.1.4.dist-info/METADATA
wework-0.1.4.dist-info/WHEEL
wework-0.1.4.dist-info/top_level.txt
wework-0.1.4.dist-info/RECORD
