Metadata-Version: 2.1
Name: wework
Version: 0.1.4
Summary: Official lib of wework.
Home-page: https://github.com/iamsk/wework
Author: UNKNOWN
Author-email: UNKNOWN
License: UNKNOWN
Platform: UNKNOWN
Requires-Dist: requests (>=2.12.4)
Requires-Dist: pycrypto (>=2.6)
